CHANGELOG.txt
LICENCE.txt
MANIFEST.in
README.txt
setup.py
RS/__init__.py
RS.egg-info/SOURCES.txt
RS.egg-info/dependency_links.txt
RS.egg-info/top_level.txt
RSTry12.egg-info/PKG-INFO
RSTry12.egg-info/SOURCES.txt
RSTry12.egg-info/dependency_links.txt
RSTry12.egg-info/top_level.txt