Metadata-Version: 1.1
Name: RSTry12
Version: 0.0.1
Summary: TESTS calculator
Home-page: UNKNOWN
Author: Houssem AZZAG
Author-email: Houssemneuer0@gmail.com
License: MIT
Keywords: calculator
Platform: UNKNOWN
Classifier: Development Status :: 5 - Production/Stable
Classifier: Intended Audience :: Education
Classifier: Operating System :: Microsoft :: Windows :: Windows 10
Classifier: License :: OSI Approved :: MIT License
Classifier: Programming Language :: Python :: 3
